cli/__init__.py
cli/args.py
cli/logger.py
cli/runner.py
rel/__init__.py
rel/batch_config/batch_config.rel
rel/batch_config/workflow/workflow.rel
rel/batch_config/workflow/steps/configure_sources.rel
rel/batch_config/workflow/steps/execute_command.rel
rel/batch_config/workflow/steps/export.rel
rel/batch_config/workflow/steps/install_models.rel
rel/batch_config/workflow/steps/invoke_solver.rel
rel/batch_config/workflow/steps/load_data.rel
rel/batch_config/workflow/steps/materialize.rel
rel/source_configs/config.rel
rel/source_configs/data_reload.rel
rel/util/snapshot_diff.rel
workflow/__init__.py
workflow/blob.py
workflow/common.py
workflow/constants.py
workflow/exception.py
workflow/executor.py
workflow/manager.py
workflow/paths.py
workflow/query.py
workflow/rai.py
workflow/rest.py
workflow/schema.py
workflow/snow.py
workflow/utils.py
rai_workflow_manager-0.0.51.dist-info/LICENSE
rai_workflow_manager-0.0.51.dist-info/METADATA
rai_workflow_manager-0.0.51.dist-info/WHEEL
rai_workflow_manager-0.0.51.dist-info/entry_points.txt
rai_workflow_manager-0.0.51.dist-info/top_level.txt
rai_workflow_manager-0.0.51.dist-info/RECORD
