Metadata-Version: 2.1
Name: rai-workflow-manager
Version: 0.0.51
Summary: The RelationalAI Workflow Manager for batch runs
Home-page: https://github.com/RelationalAI/rai-workflow-manager
Author: RelationalAI, Inc.
License: http://www.apache.org/licenses/LICENSE-2.0
Classifier: Development Status :: 3 - Alpha
Classifier: Intended Audience :: Developers
Classifier: Natural Language :: English
Classifier: License :: OSI Approved :: Apache Software License
Classifier: Programming Language :: Python :: 3.9
License-File: LICENSE
Requires-Dist: tomli ==2.0.1
Requires-Dist: pyyaml ==6.0.1
Requires-Dist: schema ==0.7.5
Requires-Dist: rai-sdk ==0.6.19
Requires-Dist: requests ==2.31.0
Requires-Dist: more-itertools ==10.1.0
Requires-Dist: azure-storage-blob ==12.17.0
Requires-Dist: snowflake-connector-python ==3.2.0
